 [
      {
        "name": "Software Development"
      },
      {
        "name": "Data Science"
      },
      {
        "name": "Web Design"
      },
      {
        "name": "Digital Marketing"
      },
      {
        "name": "Human Resources"
      },
      {
        "name": "Finance"
      },
      {
        "name": "Sales"
      },
      {
        "name": "Graphic Design"
      },
      {
        "name": "Product Management"
      },
      {
        "name": "Content Writing"
      },
      {
        "name": "Software Engineer"
      },
      {
        "name": "Data Engineer"
      },
      {
        "name": "Web Developer"
      },
      {
        "name": "Digital Marketing Specialist"
      },
      {
        "name": "HR Manager"
      },
      {
        "name": "Financial Analyst"
      },
      {
        "name": "Sales Representative"
      },
      {
        "name": "Graphic Designer"
      },
      {
        "name": "Product Manager"
      },
      {
        "name": "Content Strategist"
      }
    ]
